{
  "codeLens.enable": true,
  "diagnostic.errorSign": "●",
  "diagnostic.warningSign": "⚠",
  "diagnostic.infoSign": "⚬",
  "json.schemaDownload.enable": true,
  "languageserver": {
    "csharp-ls": {
      "command": "csharp-ls",
      "filetypes": ["cs"],
      "rootPatterns": ["*.csproj", ".vim/", ".git/", ".hg/"]
    },
    "css": {
      "command": "css-languageserver",
      "args": ["--stdio"],
      "filetypes": ["css", "less", "sass"]
    },
    "docker": {
      "command": "docker-langserver",
      "filetypes": ["dockerfile"],
      "args": ["--stdio"]
    },
    "ruby": {
	"command": "solargraph",
	"args": ["stdio"],
	"filetypes": ["ruby"]
    },
    "terraform": {
      "command": "terraform-lsp",
      "filetypes": ["tf", "terraform"],
      "initializationOptions": {}
    }
  },
  "yaml.schemaStore.enable": true,
  "yaml.schemas": {
    "http://json.schemastore.org/kustomization": ["kustomization.yaml"],
    "http://json.schemastore.org/cloudbuild.json": ["cloudbuild.yaml"],
    "http://json.schemastore.org/gitlab-ci.json": [
      ".gitlab-ci.yml",
      ".gitlab-ci.yaml"
    ],
    "http://json.schemastore.org/chart.json": ["chart.yaml"],
    "http://json.schemastore.org/github-action.json": ["github-action.yaml"],
    "https://json.schemastore.org/prometheus.json": ["prometheus.yaml"],
    "https://raw.githubusercontent.com/compose-spec/compose-spec/master/schema/compose-spec.json": [
      "docker-compose*.yaml"
    ],
    "https://raw.githubusercontent.com/GoogleContainerTools/skaffold/master/docs/content/en/schemas/v2beta19.json": [
      "skaffold.yaml"
    ],
    "https://json.schemastore.org/github-workflow.json": ["/workflows/*.yml"],
    "kubernetes": ["/*.yaml"]
  },
  "yaml.validate": true,
  "coc.preferences.extensionUpdateCheck": "daily"
}
